aiqDocTests-1.7.1.data/scripts/aiqdoctests
aiqdoctests/.aiqdoctests.config
aiqdoctests/__init__.py
aiqdoctests/structures.py
aiqdoctests/wait
aiqDocTests-1.7.1.dist-info/LICENSE
aiqDocTests-1.7.1.dist-info/METADATA
aiqDocTests-1.7.1.dist-info/WHEEL
aiqDocTests-1.7.1.dist-info/top_level.txt
aiqDocTests-1.7.1.dist-info/RECORD
