Metadata-Version: 2.1
Name: aiqDocTests
Version: 1.7.1
Summary: A framework to validate request/response's json and create documentation for REST API
Home-page: https://github.com/aiqfome/aiqDocTests
Author: An Awesome Coder
Author-email: dev@aiqfome.com
License: Apache License 2.0
Platform: UNKNOWN
Classifier: License :: OSI Approved :: Apache Software License
Classifier: Programming Language :: Python :: 3
Classifier: Operating System :: OS Independent
Classifier: Topic :: Software Development :: Testing
Classifier: Topic :: Text Editors :: Documentation
Requires-Dist: cerberus
Requires-Dist: requests
Requires-Dist: flask-swagger-ui
